hex_utils/__init__.py
hex_utils/asc.py
hex_utils/asc2asc.py
hex_utils/asc2hasc.py
hex_utils/csv2asc.py
hex_utils/csv2hasc.py
hex_utils/csv2interpol.py
hex_utils/hasc.py
hex_utils/hasc2geojson.py
hex_utils/hasc2gml.py
hex_utils/parserExtent.py
hex_utils/parserSurface.py
hex_utils/raster.py
hex_utils/surface2asc.py
hex_utils/surface2hasc.py
surfaces/__init__.py
surfaces/channel.py
surfaces/eat2.py
surfaces/eat2Gaussian.py
surfaces/eat2Hubbert.py
surfaces/pit.py
surfaces/pitGaussian.py
surfaces/pitHubbert.py
surfaces/surface.py
tests/__init__.py
tests/test_optional_headers.py
hex_utils-0.4.7.dist-info/LICENCE
hex_utils-0.4.7.dist-info/METADATA
hex_utils-0.4.7.dist-info/WHEEL
hex_utils-0.4.7.dist-info/entry_points.txt
hex_utils-0.4.7.dist-info/top_level.txt
hex_utils-0.4.7.dist-info/RECORD
