Metadata-Version: 2.1
Name: hex-utils
Version: 0.4.7
Summary: Utilities for ASCII encoded hexagonal rasters (HexASCII)
Home-page: https://codeberg.org/ldesousa/hex-utils
Author: Luís Moreira de Sousa
Author-email: luis.de.sousa@protonmail.ch
License: EUPL v1.1
Keywords: hexagon hexagonal raster HexASCII
Platform: UNKNOWN
Classifier: Programming Language :: Python
Classifier: Programming Language :: Python :: 3
Classifier: Development Status :: 4 - Beta
Classifier: Environment :: Console
Classifier: Intended Audience :: Science/Research
Classifier: License :: OSI Approved :: European Union Public Licence 1.1 (EUPL 1.1)
Classifier: Operating System :: OS Independent
Classifier: Topic :: Scientific/Engineering :: GIS
License-File: LICENCE
Requires-Dist: cycler
Requires-Dist: numpy
Requires-Dist: pyparsing
Requires-Dist: python-dateutil
Requires-Dist: pytz
Requires-Dist: scipy
Requires-Dist: six
